recmodule/__init__.py
recmodule/recmodule.py
recmodule-0.0.1.dist-info/LICENSE
recmodule-0.0.1.dist-info/METADATA
recmodule-0.0.1.dist-info/WHEEL
recmodule-0.0.1.dist-info/top_level.txt
recmodule-0.0.1.dist-info/RECORD
