Metadata-Version: 2.1
Name: recmodule
Version: 0.0.1
Summary: This module contain functions that can help make PAR easier and faster
Home-page: https://stash.customappsteam.co.uk/users/dakuoko/repos/recmodule/browse
Author: KPMG-FL
Author-email: ukdlcloudopsfrontline@kpmg.co.uk
License: UNKNOWN
Platform: UNKNOWN
Classifier: Programming Language :: Python :: 3
Classifier: License :: OSI Approved :: MIT License
Classifier: Operating System :: OS Independent
Requires-Python: >=3.6
